alu.v
`timescale 1ns / 1ps
//////////////////////////////////////////////////////////////////////////////////
// Company: 
// Engineer: 
// 
// Create Date: 08.07.2025 15:07:38
// Design Name: 
// Module Name: alu
// Project Name: 
// Target Devices: 
// Tool Versions: 
// Description: 
// 
// Dependencies: 
// 
// Revision:
// Revision 0.01 - File Created
// Additional Comments:
// 
//////////////////////////////////////////////////////////////////////////////////


module alu(
    input [7:0] x,
    input [7:0] y,
    input [3:0] sel,
    output reg [7:0] out,
    output reg zero,
    output reg carry,
    output reg overflow,
    output reg negative
    );
    reg [15:0]product;
    parameter Add = 0, Sub = 1,
              MUL = 2, AND = 3,
              OR = 4, XOR = 5,XNOR=6,
                NOT = 7, NAND =8,
               NOR= 9, SLT = 10,
              SLL = 11, SLR= 12,
              ROL = 13, ROR = 14;
    always @(*)begin
    carry=0;overflow=0;
    case(sel)
    Add: begin
    {carry,out}=x+y;
    overflow=(~x[7]&~y[7]&out[7])|(x[7]&y[7]&~out[7]);
    end
    Sub:begin  
    {carry,out}=x-y;
    overflow=(x[7]& ~y[7]& ~out[7]) | (~x[7] & y[7] & out[7]);
    end
    MUL: begin
    product=x*y;
    out=product[7:0]
    overflow=|product[15:8];
    end
        
    AND:out=x&y;
    OR:out=x|y;
    XOR:out=x^y;
    XNOR:out=~(x^y);
    NOT:out=~x;
    NAND:out=~(x & y);
    NOR:out=(~x|y);
    SLT:out=(x<y)?8'd1:8'd0;
    SLL:out=x<<1;
    SLR:out=x>>1;
    ROL:out={x[6:0],x[7]};
    ROR:out={x[0],x[7:1]};
    default:out=8'd0;
    endcase
    negative=out[7];
     zero=(out==8'd0)?1'b1:1'b0;
     end
endmodule

alu_tb.v
`timescale 1ns / 1ps
//////////////////////////////////////////////////////////////////////////////////
// Company: 
// Engineer: 
// 
// Create Date: 08.07.2025 15:22:34
// Design Name: 
// Module Name: alu_tb
// Project Name: 
// Target Devices: 
// Tool Versions: 
// Description: 
// 
// Dependencies: 
// 
// Revision:
// Revision 0.01 - File Created
// Additional Comments:
// 
//////////////////////////////////////////////////////////////////////////////////


module alu_tb();
 reg  [7:0] x,y;
 reg  [3:0] sel;
 wire [7:0] out;
 wire zero,carry,overflow,negative;
 alu uut(x,y,sel,out,zero,carry,overflow,negative);
 initial begin
 $display("ALU Testbench Starts");
 $monitor("x=%d y=%d sel=%b -> out=%d zero=%b carry=%b overflow=%b negative=%b", x, y, sel, out, zero,carry,overflow,negative);
 x=8'd25;y=8'd15;
 sel=0;
 #10 sel=1;
 #10 sel=2;
 #10 sel=3;
 #10 sel=4;
 #10 sel=5;
 #10 sel=6;
 #10 sel=7;
 #10 sel=8;
 #10 sel=9;
 #10 sel=10;
 #10 sel=11;
 #10 sel=12;
 #10 sel=13;
 #10 sel=14;
 
 #10 x=8'd128;y=8'd128;
 sel=0;
 #10 sel=1;
 #10 sel=2;
 #10 sel=3;
 #10 sel=4;
 #10 sel=5;
 #10 sel=6;
 #10 sel=7;
 #10 sel=8;
 #10 sel=9;
 #10 sel=10;
 #10 sel=11;
 #10 sel=12;
 #10 sel=13;
 #10 sel=14;
 $finish;
 end
 initial begin
    $dumpfile("wave.vcd");    // This tells the simulator to generate the file
    $dumpvars(0, alu_tb);     // This dumps all variables in alu_tb
end
endmodule

wave.vcd
$date
   Tue Jul  8 23:48:50 2025
$end

$version
  2024.1
  $dumpfile ("wave.vcd") 
$end

$timescale
  1ps
$end

$scope module alu_tb $end
$var reg 8 ! x [7:0] $end
$var reg 8 " y [7:0] $end
$var reg 4 # sel [3:0] $end
$var wire 8 $ out [7:0] $end
$var wire 1 % zero $end
$var wire 1 & carry $end
$var wire 1 ' overflow $end
$var wire 1 ( negative $end
$scope module uut $end
$var wire 8 ) x [7:0] $end
$var wire 8 * y [7:0] $end
$var wire 4 + sel [3:0] $end
$var reg 8 , out [7:0] $end
$var reg 1 - zero $end
$var reg 1 . carry $end
$var reg 1 / overflow $end
$var reg 1 0 negative $end
$var reg 16 1 product [15:0] $end
$upscope $end
$upscope $end
$enddefinitions $end

#0
$dumpvars
b11001 !
b1111 "
b0 #
b101000 $
0%
0&
0'
0(
b11001 )
b1111 *
b0 +
b101000 ,
0-
0.
0/
00
bx 1
$end

#10000
b1 #
b1010 $
b1 +
b1010 ,

#20000
b10 #
b1110111 $
1'
b10 +
b1110111 ,
1/
b101110111 1

#30000
b11 #
b1001 $
0'
b11 +
b1001 ,
0/

#40000
b100 #
b11111 $
b100 +
b11111 ,

#50000
b101 #
b10110 $
b101 +
b10110 ,

#60000
b110 #
b11101001 $
1(
b110 +
b11101001 ,
10

#70000
b111 #
b11100110 $
b111 +
b11100110 ,

#80000
b1000 #
b11110110 $
b1000 +
b11110110 ,

#90000
b1001 #
b11101111 $
b1001 +
b11101111 ,

#100000
b1010 #
b0 $
1%
0(
b1010 +
b0 ,
1-
00

#110000
b1011 #
b110010 $
0%
b1011 +
b110010 ,
0-

#120000
b1100 #
b1100 $
b1100 +
b1100 ,

#130000
b1101 #
b110010 $
b1101 +
b110010 ,

#140000
b1110 #
b10001100 $
1(
b1110 +
b10001100 ,
10

#150000
b10000000 !
b10000000 "
b0 #
b0 $
1%
1&
1'
0(
b10000000 )
b10000000 *
b0 +
b0 ,
1-
1.
1/
00

#160000
b1 #
0&
0'
b1 +
0.
0/

#170000
b10 #
1'
b10 +
1/
b100000000000000 1

#180000
b11 #
b10000000 $
0%
0'
1(
b11 +
b10000000 ,
0-
0/
10

#190000
b100 #
b100 +

#200000
b101 #
b0 $
1%
0(
b101 +
b0 ,
1-
00

#210000
b110 #
b11111111 $
0%
1(
b110 +
b11111111 ,
0-
10

#220000
b111 #
b1111111 $
0(
b111 +
b1111111 ,
00

#230000
b1000 #
b1000 +

#240000
b1001 #
b11111111 $
1(
b1001 +
b11111111 ,
10

#250000
b1010 #
b0 $
1%
0(
b1010 +
b0 ,
1-
00

#260000
b1011 #
b1011 +

#270000
b1100 #
b1000000 $
0%
b1100 +
b1000000 ,
0-

#280000
b1101 #
b1 $
b1101 +
b1 ,

#290000
b1110 #
b1000000 $
b1110 +
b1000000 ,
